flameEngine/__init__.py
flameEngine/example.py
flameEngine/flame.py
flameEngine-0.0.4.37.dist-info/METADATA
flameEngine-0.0.4.37.dist-info/WHEEL
flameEngine-0.0.4.37.dist-info/license.txt
flameEngine-0.0.4.37.dist-info/top_level.txt
flameEngine-0.0.4.37.dist-info/RECORD
