Metadata-Version: 2.1
Name: flameEngine
Version: 0.0.4.37
Summary: Flame simulation package
Author: Piotr Mikolajczyk
Author-email: <pio.mikolajczyk@email.com>
Keywords: python,flameEngine package,flameEngine,flameEngine
Classifier: Development Status :: 3 - Alpha
Classifier: Intended Audience :: Education
Classifier: Programming Language :: Python :: 3
Classifier: Operating System :: MacOS :: MacOS X
Classifier: Operating System :: Microsoft :: Windows
License-File: license.txt
